{
    "line.clr.has_term": [
        {
            "comment": "line number",
            "foreground": "blue",
            "background": "reset"
        },
        {
            "comment": "actual line",
            "foreground": "green",
            "background": "reset"
        }
    ],
    "line.clr.no_term": [
        {
            "comment": "line number",
            "foreground": "blue",
            "background": "reset"
        },
        {
            "comment": "actual line",
            "foreground": "red",
            "background": "reset"
        }
    ],
	"default.include_filename": false,
	"default.context": 0,
	"default.in_cwd": false
}